dagpipy/__init__.py
dagpipy/client.py
dagpipy/enums.py
dagpipy/exceptions.py
dagpipy/models/__init__.py
dagpipy/models/games.py
dagpipy/models/imageurl.py
dagpipy-1.1.1.dist-info/LICENSE
dagpipy-1.1.1.dist-info/METADATA
dagpipy-1.1.1.dist-info/WHEEL
dagpipy-1.1.1.dist-info/top_level.txt
dagpipy-1.1.1.dist-info/RECORD
