Metadata-Version: 2.1
Name: dagpipy
Version: 1.1.1
Summary: A Python API Wrapper for https://dagpi.xyz/, the fast and free image API.
Home-page: https://github.com/niztg/dagpipy
Author: niztg
License: MIT
Project-URL: Discord Server, https://discord.com/invite/2fxKxJH
Project-URL: Documentation, https://github.com/niztg/dagpipy/blob/master/DOCUMENTATION.md
Platform: UNKNOWN
Requires-Python: >=2.7, !=3.0.*, !=3.1.*, !=3.2.*, !=3.3.*, !=3.4.*
Requires-Dist: requests
